<?xml version="1.0" encoding="UTF-8"?><DataFlowResults FileFormatVersion="102" TerminationState="Success"><Results><Result><Sink Statement="virtualinvoke $r7.&lt;net.luniks.android.inetify.LocationMapView: void sendBroadcast(android.content.Intent)&gt;(r2)" Method="&lt;net.luniks.android.inetify.LocationMapView$LocateTask: void onPostExecute(java.lang.Void)&gt;"><AccessPath Value="r2" Type="android.content.Intent" TaintSubFields="true"><Fields><Field Value="&lt;android.content.Intent: java.lang.Object[] extraValues&gt;" Type="java.lang.Object[]"></Field></Fields></AccessPath></Sink><Sources><Source Statement="$r2 = virtualinvoke $r3.&lt;android.location.LocationManager: android.location.Location getLastKnownLocation(java.lang.String)&gt;($r1)" Method="&lt;net.luniks.android.impl.LocationManagerImpl: android.location.Location getLastKnownLocation(java.lang.String)&gt;"><AccessPath Value="$r2" Type="android.location.Location" TaintSubFields="true"></AccessPath></Source></Sources></Result><Result><Sink Statement="virtualinvoke $r1.&lt;android.os.Bundle: void putString(java.lang.String,java.lang.String)&gt;(&quot;selectedSSID&quot;, $r2)" Method="&lt;net.luniks.android.inetify.IgnoreList: void onSaveInstanceState(android.os.Bundle)&gt;"><AccessPath Value="$r2" Type="java.lang.String" TaintSubFields="true"></AccessPath></Sink><Sources><Source Statement="$r7 = interfaceinvoke r6.&lt;android.database.Cursor: java.lang.String getString(int)&gt;(2)" Method="&lt;net.luniks.android.inetify.IgnoreList$2: boolean onItemLongClick(android.widget.AdapterView,android.view.View,int,long)&gt;"><AccessPath Value="$r7" Type="java.lang.String" TaintSubFields="true"></AccessPath></Source></Sources></Result><Result><Sink Statement="virtualinvoke $r1.&lt;android.os.Bundle: void putString(java.lang.String,java.lang.String)&gt;(&quot;selectedBSSID&quot;, $r2)" Method="&lt;net.luniks.android.inetify.LocationList: void onSaveInstanceState(android.os.Bundle)&gt;"><AccessPath Value="$r2" Type="java.lang.String" TaintSubFields="true"></AccessPath></Sink><Sources><Source Statement="$r7 = interfaceinvoke r6.&lt;android.database.Cursor: java.lang.String getString(int)&gt;(1)" Method="&lt;net.luniks.android.inetify.LocationList$2: boolean onItemLongClick(android.widget.AdapterView,android.view.View,int,long)&gt;"><AccessPath Value="$r7" Type="java.lang.String" TaintSubFields="true"></AccessPath></Source></Sources></Result><Result><Sink Statement="$r3 = virtualinvoke r0.&lt;net.luniks.android.inetify.LocationList: android.content.Intent registerReceiver(android.content.BroadcastReceiver,android.content.IntentFilter)&gt;($r4, r1)" Method="&lt;net.luniks.android.inetify.LocationList: void onResume()&gt;"><AccessPath Value="r0" Type="net.luniks.android.inetify.LocationList" TaintSubFields="true"><Fields><Field Value="&lt;net.luniks.android.inetify.LocationList: java.lang.String selectedBSSID&gt;" Type="java.lang.String"></Field></Fields></AccessPath></Sink><Sources><Source Statement="$r7 = interfaceinvoke r6.&lt;android.database.Cursor: java.lang.String getString(int)&gt;(1)" Method="&lt;net.luniks.android.inetify.LocationList$2: boolean onItemLongClick(android.widget.AdapterView,android.view.View,int,long)&gt;"><AccessPath Value="$r7" Type="java.lang.String" TaintSubFields="true"></AccessPath></Source><Source Statement="$r7 = interfaceinvoke r6.&lt;android.database.Cursor: java.lang.String getString(int)&gt;(3)" Method="&lt;net.luniks.android.inetify.LocationList$2: boolean onItemLongClick(android.widget.AdapterView,android.view.View,int,long)&gt;"><AccessPath Value="$r7" Type="java.lang.String" TaintSubFields="true"></AccessPath></Source></Sources></Result><Result><Sink Statement="$r3 = virtualinvoke r0.&lt;net.luniks.android.inetify.IgnoreList: android.content.Intent registerReceiver(android.content.BroadcastReceiver,android.content.IntentFilter)&gt;($r4, r1)" Method="&lt;net.luniks.android.inetify.IgnoreList: void onResume()&gt;"><AccessPath Value="r0" Type="net.luniks.android.inetify.IgnoreList" TaintSubFields="true"><Fields><Field Value="&lt;net.luniks.android.inetify.IgnoreList: java.lang.String selectedSSID&gt;" Type="java.lang.String"></Field></Fields></AccessPath></Sink><Sources><Source Statement="$r7 = interfaceinvoke r6.&lt;android.database.Cursor: java.lang.String getString(int)&gt;(2)" Method="&lt;net.luniks.android.inetify.IgnoreList$2: boolean onItemLongClick(android.widget.AdapterView,android.view.View,int,long)&gt;"><AccessPath Value="$r7" Type="java.lang.String" TaintSubFields="true"></AccessPath></Source></Sources></Result><Result><Sink Statement="virtualinvoke $r1.&lt;android.os.Bundle: void putString(java.lang.String,java.lang.String)&gt;(&quot;selectedName&quot;, $r2)" Method="&lt;net.luniks.android.inetify.LocationList: void onSaveInstanceState(android.os.Bundle)&gt;"><AccessPath Value="$r1" Type="android.os.Bundle" TaintSubFields="true"><Fields><Field Value="&lt;android.os.BaseBundle: java.lang.Object[] values&gt;" Type="java.lang.String"></Field></Fields></AccessPath></Sink><Sources><Source Statement="$r7 = interfaceinvoke r6.&lt;android.database.Cursor: java.lang.String getString(int)&gt;(1)" Method="&lt;net.luniks.android.inetify.LocationList$2: boolean onItemLongClick(android.widget.AdapterView,android.view.View,int,long)&gt;"><AccessPath Value="$r7" Type="java.lang.String" TaintSubFields="true"></AccessPath></Source><Source Statement="$r7 = interfaceinvoke r6.&lt;android.database.Cursor: java.lang.String getString(int)&gt;(3)" Method="&lt;net.luniks.android.inetify.LocationList$2: boolean onItemLongClick(android.widget.AdapterView,android.view.View,int,long)&gt;"><AccessPath Value="$r7" Type="java.lang.String" TaintSubFields="true"></AccessPath></Source></Sources></Result><Result><Sink Statement="virtualinvoke r2.&lt;java.io.ByteArrayOutputStream: void write(byte[],int,int)&gt;(r1, 0, $i0)" Method="&lt;org.jsoup.helper.DataUtil: java.nio.ByteBuffer readToByteBuffer(java.io.InputStream)&gt;"><AccessPath Value="r2" Type="java.io.ByteArrayOutputStream" TaintSubFields="true"><Fields><Field Value="&lt;java.io.OutputStream: byte[] innerArray&gt;" Type="byte[]"></Field></Fields></AccessPath></Sink><Sources><Source Statement="$r22 = virtualinvoke $r7.&lt;java.net.HttpURLConnection: java.io.InputStream getInputStream()&gt;()" Method="&lt;org.jsoup.helper.HttpConnection$Response: org.jsoup.helper.HttpConnection$Response execute(org.jsoup.Connection$Request,org.jsoup.helper.HttpConnection$Response)&gt;"><AccessPath Value="$r22" Type="java.io.InputStream" TaintSubFields="true"></AccessPath></Source><Source Statement="$r22 = virtualinvoke $r7.&lt;java.net.HttpURLConnection: java.io.InputStream getInputStream()&gt;()" Method="&lt;org.jsoup.helper.HttpConnection$Response: org.jsoup.helper.HttpConnection$Response execute(org.jsoup.Connection$Request,org.jsoup.helper.HttpConnection$Response)&gt;"><AccessPath Value="$r22" Type="java.io.InputStream" TaintSubFields="true"></AccessPath></Source></Sources></Result></Results><PerformanceData><PerformanceEntry Name="CallgraphConstructionSeconds" Value="6"></PerformanceEntry><PerformanceEntry Name="TaintPropagationSeconds" Value="4"></PerformanceEntry><PerformanceEntry Name="TotalRuntimeSeconds" Value="10"></PerformanceEntry><PerformanceEntry Name="MaxMemoryConsumption" Value="874"></PerformanceEntry><PerformanceEntry Name="SourceCount" Value="18"></PerformanceEntry><PerformanceEntry Name="SinkCount" Value="36"></PerformanceEntry></PerformanceData></DataFlowResults>