<?xml version="1.0" encoding="UTF-8"?><DataFlowResults FileFormatVersion="102" TerminationState="Success"><Results><Result><Sink Statement="virtualinvoke $r3.&lt;net.sf.andhsli.hotspotlogin.HotspotLoginActivity: android.content.ComponentName startService(android.content.Intent)&gt;($r6)" Method="&lt;net.sf.andhsli.hotspotlogin.HotspotLoginActivity$2: void onClick(android.view.View)&gt;"><AccessPath Value="$r3" Type="net.sf.andhsli.hotspotlogin.HotspotLoginActivity" TaintSubFields="true"><Fields><Field Value="&lt;net.sf.andhsli.hotspotlogin.HotspotLoginActivity: android.widget.EditText mPW&gt;" Type="android.widget.EditText"></Field><Field Value="&lt;android.widget.TextView: android.text.Editable content&gt;" Type="android.text.Editable"></Field></Fields></AccessPath></Sink><Sources><Source Statement="$r4 = virtualinvoke r0.&lt;net.sf.andhsli.hotspotlogin.HotspotLoginActivity: android.view.View findViewById(int)&gt;(2131296258)" Category="Password Input" Method="&lt;net.sf.andhsli.hotspotlogin.HotspotLoginActivity: void onCreate(android.os.Bundle)&gt;"><AccessPath Value="$r4" Type="android.widget.TextView" TaintSubFields="true"><Fields><Field Value="&lt;android.widget.TextView: android.text.Editable content&gt;" Type="android.text.Editable"></Field></Fields></AccessPath></Source></Sources></Result><Result><Sink Statement="virtualinvoke r0.&lt;net.sf.andhsli.hotspotlogin.HotspotLoginMonitorActivity$UIHandler: boolean sendMessage(android.os.Message)&gt;($r2)" Method="&lt;net.sf.andhsli.hotspotlogin.HotspotLoginMonitorActivity$UIHandler: void log(java.lang.String)&gt;"><AccessPath Value="$r2" Type="android.os.Message" TaintSubFields="true"><Fields><Field Value="&lt;android.os.Message: java.lang.Object obj&gt;" Type="java.lang.String"></Field></Fields></AccessPath></Sink><Sources><Source Statement="$r8 = virtualinvoke $r9.&lt;android.net.wifi.WifiInfo: java.lang.String getSSID()&gt;()" Method="&lt;net.sf.andhsli.hotspotlogin.HotspotLoginMonitorActivity$4: void exec()&gt;"><AccessPath Value="$r8" Type="java.lang.String" TaintSubFields="true"></AccessPath></Source><Source Statement="$r7 = virtualinvoke $r4.&lt;android.net.wifi.WifiInfo: java.lang.String getSSID()&gt;()" Method="&lt;net.sf.andhsli.hotspotlogin.HotspotLoginMonitorActivity$6: void exec()&gt;"><AccessPath Value="$r7" Type="java.lang.String" TaintSubFields="true"></AccessPath></Source><Source Statement="$r21 = interfaceinvoke $r19.&lt;org.apache.http.HttpResponse: org.apache.http.HttpEntity getEntity()&gt;()" Method="&lt;net.sf.andhsli.hotspotlogin.HotspotUtilities: java.lang.String httpPost(java.lang.String,java.lang.String[][],java.lang.String)&gt;"><AccessPath Value="$r21" Type="org.apache.http.HttpEntity" TaintSubFields="true"></AccessPath></Source><Source Statement="$r13 = interfaceinvoke $r8.&lt;org.apache.http.HttpResponse: org.apache.http.HttpEntity getEntity()&gt;()" Method="&lt;net.sf.andhsli.hotspotlogin.HotspotUtilities: java.lang.String httpGet(java.lang.String,java.lang.String)&gt;"><AccessPath Value="$r13" Type="org.apache.http.HttpEntity" TaintSubFields="true"></AccessPath></Source></Sources></Result><Result><Sink Statement="virtualinvoke r0.&lt;net.sf.andhsli.hotspotlogin.HotspotLoginActivity: void startActivityForResult(android.content.Intent,int)&gt;($r4, 1)" Method="&lt;net.sf.andhsli.hotspotlogin.HotspotLoginActivity: boolean onOptionsItemSelected(android.view.MenuItem)&gt;"><AccessPath Value="r0" Type="net.sf.andhsli.hotspotlogin.HotspotLoginActivity" TaintSubFields="true"><Fields><Field Value="&lt;net.sf.andhsli.hotspotlogin.HotspotLoginActivity: android.widget.EditText mPW&gt;" Type="android.widget.EditText"></Field><Field Value="&lt;android.widget.TextView: android.text.Editable content&gt;" Type="android.text.Editable"></Field></Fields></AccessPath></Sink><Sources><Source Statement="$r4 = virtualinvoke r0.&lt;net.sf.andhsli.hotspotlogin.HotspotLoginActivity: android.view.View findViewById(int)&gt;(2131296258)" Category="Password Input" Method="&lt;net.sf.andhsli.hotspotlogin.HotspotLoginActivity: void onCreate(android.os.Bundle)&gt;"><AccessPath Value="$r4" Type="android.widget.TextView" TaintSubFields="true"><Fields><Field Value="&lt;android.widget.TextView: android.text.Editable content&gt;" Type="android.text.Editable"></Field></Fields></AccessPath></Source></Sources></Result><Result><Sink Statement="staticinvoke &lt;android.util.Log: int i(java.lang.String,java.lang.String)&gt;($r0, $r1)" Method="&lt;net.sf.andhsli.hotspotlogin.Log: void i(java.lang.String,java.lang.String)&gt;"><AccessPath Value="$r1" Type="java.lang.String" TaintSubFields="true"></AccessPath></Sink><Sources><Source Statement="$r7 = virtualinvoke $r4.&lt;android.net.wifi.WifiInfo: java.lang.String getSSID()&gt;()" Method="&lt;net.sf.andhsli.hotspotlogin.HotspotLoginMonitorActivity$6: void exec()&gt;"><AccessPath Value="$r7" Type="java.lang.String" TaintSubFields="true"></AccessPath></Source><Source Statement="$r8 = virtualinvoke $r9.&lt;android.net.wifi.WifiInfo: java.lang.String getSSID()&gt;()" Method="&lt;net.sf.andhsli.hotspotlogin.HotspotLoginMonitorActivity$4: void exec()&gt;"><AccessPath Value="$r8" Type="java.lang.String" TaintSubFields="true"></AccessPath></Source></Sources></Result><Result><Sink Statement="virtualinvoke r0.&lt;net.sf.andhsli.hotspotlogin.HotspotLoginActivity: boolean bindService(android.content.Intent,android.content.ServiceConnection,int)&gt;($r2, $r5, 1)" Method="&lt;net.sf.andhsli.hotspotlogin.HotspotLoginActivity: void bindHsliService()&gt;"><AccessPath Value="r0" Type="net.sf.andhsli.hotspotlogin.HotspotLoginActivity" TaintSubFields="true"><Fields><Field Value="&lt;net.sf.andhsli.hotspotlogin.HotspotLoginActivity: android.widget.EditText mPW&gt;" Type="android.widget.EditText"></Field><Field Value="&lt;android.widget.TextView: android.text.Editable content&gt;" Type="android.text.Editable"></Field></Fields></AccessPath></Sink><Sources><Source Statement="$r4 = virtualinvoke r0.&lt;net.sf.andhsli.hotspotlogin.HotspotLoginActivity: android.view.View findViewById(int)&gt;(2131296258)" Category="Password Input" Method="&lt;net.sf.andhsli.hotspotlogin.HotspotLoginActivity: void onCreate(android.os.Bundle)&gt;"><AccessPath Value="$r4" Type="android.widget.TextView" TaintSubFields="true"><Fields><Field Value="&lt;android.widget.TextView: android.text.Editable content&gt;" Type="android.text.Editable"></Field></Fields></AccessPath></Source></Sources></Result></Results><PerformanceData><PerformanceEntry Name="CallgraphConstructionSeconds" Value="2"></PerformanceEntry><PerformanceEntry Name="TotalRuntimeSeconds" Value="2"></PerformanceEntry><PerformanceEntry Name="MaxMemoryConsumption" Value="160"></PerformanceEntry><PerformanceEntry Name="SourceCount" Value="14"></PerformanceEntry><PerformanceEntry Name="SinkCount" Value="25"></PerformanceEntry></PerformanceData></DataFlowResults>