<?xml version="1.0" encoding="UTF-8"?><DataFlowResults FileFormatVersion="102" TerminationState="Success"><Results><Result><Sink Statement="virtualinvoke r2.&lt;android.content.ContentResolver: int update(android.net.Uri,android.content.ContentValues,java.lang.String,java.lang.String[])&gt;($r9, r3, &quot;_id=?&quot;, $r4)" Method="&lt;ch.blinkenlights.android.apnswitch.ApnDao: boolean disableApnList(java.util.List)&gt;"><AccessPath Value="$r4" Type="java.lang.String[]" TaintSubFields="true"></AccessPath></Sink><Sources><Source Statement="$r5 = interfaceinvoke $r1.&lt;android.database.Cursor: java.lang.String getString(int)&gt;(2)" Method="&lt;ch.blinkenlights.android.apnswitch.ApnDao: java.util.List createApnList(android.database.Cursor)&gt;"><AccessPath Value="$r5" Type="java.lang.String" TaintSubFields="true"></AccessPath></Source><Source Statement="$r3 = interfaceinvoke $r1.&lt;android.database.Cursor: java.lang.String getString(int)&gt;(0)" Method="&lt;ch.blinkenlights.android.apnswitch.ApnDao: java.util.List createApnList(android.database.Cursor)&gt;"><AccessPath Value="$r3" Type="java.lang.String" TaintSubFields="true"></AccessPath></Source><Source Statement="$r4 = interfaceinvoke $r1.&lt;android.database.Cursor: java.lang.String getString(int)&gt;(1)" Method="&lt;ch.blinkenlights.android.apnswitch.ApnDao: java.util.List createApnList(android.database.Cursor)&gt;"><AccessPath Value="$r4" Type="java.lang.String" TaintSubFields="true"></AccessPath></Source></Sources></Result><Result><Sink Statement="virtualinvoke r2.&lt;android.content.ContentResolver: int update(android.net.Uri,android.content.ContentValues,java.lang.String,java.lang.String[])&gt;($r10, r3, &quot;_id=?&quot;, $r4)" Method="&lt;ch.blinkenlights.android.apnswitch.ApnDao: boolean enableApnList(java.util.List)&gt;"><AccessPath Value="$r4" Type="java.lang.String[]" TaintSubFields="true"></AccessPath></Sink><Sources><Source Statement="$r5 = interfaceinvoke $r1.&lt;android.database.Cursor: java.lang.String getString(int)&gt;(2)" Method="&lt;ch.blinkenlights.android.apnswitch.ApnDao: java.util.List createApnList(android.database.Cursor)&gt;"><AccessPath Value="$r5" Type="java.lang.String" TaintSubFields="true"></AccessPath></Source><Source Statement="$r3 = interfaceinvoke $r1.&lt;android.database.Cursor: java.lang.String getString(int)&gt;(0)" Method="&lt;ch.blinkenlights.android.apnswitch.ApnDao: java.util.List createApnList(android.database.Cursor)&gt;"><AccessPath Value="$r3" Type="java.lang.String" TaintSubFields="true"></AccessPath></Source><Source Statement="$r4 = interfaceinvoke $r1.&lt;android.database.Cursor: java.lang.String getString(int)&gt;(1)" Method="&lt;ch.blinkenlights.android.apnswitch.ApnDao: java.util.List createApnList(android.database.Cursor)&gt;"><AccessPath Value="$r4" Type="java.lang.String" TaintSubFields="true"></AccessPath></Source></Sources></Result></Results><PerformanceData><PerformanceEntry Name="CallgraphConstructionSeconds" Value="1"></PerformanceEntry><PerformanceEntry Name="TotalRuntimeSeconds" Value="1"></PerformanceEntry><PerformanceEntry Name="MaxMemoryConsumption" Value="119"></PerformanceEntry><PerformanceEntry Name="SourceCount" Value="5"></PerformanceEntry><PerformanceEntry Name="SinkCount" Value="6"></PerformanceEntry></PerformanceData></DataFlowResults>