<?xml version="1.0" encoding="UTF-8"?><DataFlowResults FileFormatVersion="102" TerminationState="Success"><Results><Result><Sink Statement="virtualinvoke $r1.&lt;java.io.OutputStream: void write(byte[],int,int)&gt;(r2, 0, $i0)" Method="&lt;com.cradle.iitc_mobile.IITC_FileManager: void copyStream(java.io.InputStream,java.io.OutputStream,boolean)&gt;"><AccessPath Value="r2" Type="byte[]" TaintSubFields="true"></AccessPath></Sink><Sources><Source Statement="$r13 = virtualinvoke $r12.&lt;java.net.URL: java.io.InputStream openStream()&gt;()" Method="&lt;com.cradle.iitc_mobile.async.UpdateScript: java.lang.Boolean doInBackground(java.lang.String[])&gt;"><AccessPath Value="$r13" Type="java.io.InputStream" TaintSubFields="true"></AccessPath></Source><Source Statement="$r13 = virtualinvoke $r12.&lt;java.net.URL: java.io.InputStream openStream()&gt;()" Method="&lt;com.cradle.iitc_mobile.async.UpdateScript: java.lang.Boolean doInBackground(java.lang.String[])&gt;"><AccessPath Value="$r13" Type="java.io.InputStream" TaintSubFields="true"></AccessPath></Source><Source Statement="$r10 = virtualinvoke $r9.&lt;java.net.URLConnection: java.io.InputStream getInputStream()&gt;()" Method="&lt;com.cradle.iitc_mobile.IITC_FileManager$4: void run()&gt;"><AccessPath Value="$r10" Type="java.io.InputStream" TaintSubFields="true"></AccessPath></Source></Sources></Result><Result><Sink Statement="virtualinvoke r2.&lt;android.os.Bundle: void putInt(java.lang.String,int)&gt;(&quot;icon&quot;, $i1)" Method="&lt;com.cradle.iitc_mobile.share.ShareActivity: void addTab(java.util.ArrayList,int,int)&gt;"><AccessPath Value="r2" Type="android.os.Bundle" TaintSubFields="true"><Fields><Field Value="&lt;android.os.BaseBundle: java.lang.Object[] values&gt;" Type="java.lang.Object[]"></Field></Fields></AccessPath></Sink><Sources><Source Statement="$r8 = virtualinvoke $r7.&lt;android.content.pm.PackageManager: java.util.List queryIntentActivities(android.content.Intent,int)&gt;($r1, 0)" Method="&lt;com.cradle.iitc_mobile.share.IntentGenerator: java.util.ArrayList resolveTargets(android.content.Intent)&gt;"><AccessPath Value="$r8" Type="java.util.List" TaintSubFields="true"></AccessPath></Source></Sources></Result><Result><Sink Statement="$r15 = virtualinvoke $r15.&lt;android.content.Intent: android.content.Intent setComponent(android.content.ComponentName)&gt;(r3)" Method="&lt;com.cradle.iitc_mobile.share.IntentGenerator: java.util.ArrayList resolveTargets(android.content.Intent)&gt;"><AccessPath Value="r3" Type="android.content.ComponentName" TaintSubFields="true"><Fields><Field Value="&lt;android.content.ComponentName: java.lang.String mClass&gt;" Type="java.lang.String"></Field></Fields></AccessPath></Sink><Sources><Source Statement="$r8 = virtualinvoke $r7.&lt;android.content.pm.PackageManager: java.util.List queryIntentActivities(android.content.Intent,int)&gt;($r1, 0)" Method="&lt;com.cradle.iitc_mobile.share.IntentGenerator: java.util.ArrayList resolveTargets(android.content.Intent)&gt;"><AccessPath Value="$r8" Type="java.util.List" TaintSubFields="true"></AccessPath></Source></Sources></Result><Result><Sink Statement="virtualinvoke r2.&lt;android.os.Bundle: void putParcelableArrayList(java.lang.String,java.util.ArrayList)&gt;(&quot;intents&quot;, r1)" Method="&lt;com.cradle.iitc_mobile.share.ShareActivity: void addTab(java.util.ArrayList,int,int)&gt;"><AccessPath Value="r2" Type="android.os.Bundle" TaintSubFields="true"><Fields><Field Value="&lt;android.os.BaseBundle: java.lang.Object[] values&gt;" Type="java.lang.Object[]"></Field></Fields></AccessPath></Sink><Sources><Source Statement="$r8 = virtualinvoke $r7.&lt;android.content.pm.PackageManager: java.util.List queryIntentActivities(android.content.Intent,int)&gt;($r1, 0)" Method="&lt;com.cradle.iitc_mobile.share.IntentGenerator: java.util.ArrayList resolveTargets(android.content.Intent)&gt;"><AccessPath Value="$r8" Type="java.util.List" TaintSubFields="true"></AccessPath></Source></Sources></Result><Result><Sink Statement="virtualinvoke r2.&lt;android.os.Bundle: void putString(java.lang.String,java.lang.String)&gt;(&quot;title&quot;, $r4)" Method="&lt;com.cradle.iitc_mobile.share.ShareActivity: void addTab(java.util.ArrayList,int,int)&gt;"><AccessPath Value="r2" Type="android.os.Bundle" TaintSubFields="true"><Fields><Field Value="&lt;android.os.BaseBundle: java.lang.Object[] values&gt;" Type="java.lang.Object[]"></Field></Fields></AccessPath></Sink><Sources><Source Statement="$r8 = virtualinvoke $r7.&lt;android.content.pm.PackageManager: java.util.List queryIntentActivities(android.content.Intent,int)&gt;($r1, 0)" Method="&lt;com.cradle.iitc_mobile.share.IntentGenerator: java.util.ArrayList resolveTargets(android.content.Intent)&gt;"><AccessPath Value="$r8" Type="java.util.List" TaintSubFields="true"></AccessPath></Source></Sources></Result></Results><PerformanceData><PerformanceEntry Name="CallgraphConstructionSeconds" Value="2"></PerformanceEntry><PerformanceEntry Name="TotalRuntimeSeconds" Value="3"></PerformanceEntry><PerformanceEntry Name="MaxMemoryConsumption" Value="217"></PerformanceEntry><PerformanceEntry Name="SourceCount" Value="9"></PerformanceEntry><PerformanceEntry Name="SinkCount" Value="33"></PerformanceEntry></PerformanceData></DataFlowResults>